splunk_logger/__init__.py
splunk_hec_logger-0.1.5.dist-info/METADATA
splunk_hec_logger-0.1.5.dist-info/WHEEL
splunk_hec_logger-0.1.5.dist-info/top_level.txt
splunk_hec_logger-0.1.5.dist-info/RECORD
