Metadata-Version: 2.4
Name: splunk_hec_logger
Version: 0.1.5
Summary: A simple Splunk HEC logger.
Home-page: 
Author: Rostislav Anisimov
Author-email: rostislav.anisimov@gmail.com
Classifier: Programming Language :: Python :: 3
Classifier: License :: OSI Approved :: MIT License
Classifier: Operating System :: OS Independent
Requires-Python: >=3.6
Requires-Dist: requests
Dynamic: author
Dynamic: author-email
Dynamic: classifier
Dynamic: description
Dynamic: description-content-type
Dynamic: requires-dist
Dynamic: requires-python
Dynamic: summary
